d3nav/__init__.py
d3nav/__main__.py
d3nav/base.py
d3nav/cli.py
d3nav/factory.py
d3nav/metric_stp3.py
d3nav/metrics.py
d3nav/visual.py
d3nav/datasets/__init__.py
d3nav/datasets/nusc.py
d3nav/model/__init__.py
d3nav/model/base_model.py
d3nav/model/common.py
d3nav/model/d3nav.py
d3nav/model/d3nav_video.py
d3nav/model/trainer.py
d3nav/scripts/__init__.py
d3nav/scripts/train.py
d3nav/scripts/train_r34.py
d3nav/scripts/train_r34_traj.py
d3nav/scripts/train_traj.py
d3nav/scripts/visualize_d3nav.py
d3nav/scripts/visualize_pose.py
d3nav/scripts/visualize_traj.py
d3nav-1.0.0.dist-info/licenses/LICENSE
d3nav-1.0.0.dist-info/METADATA
d3nav-1.0.0.dist-info/WHEEL
d3nav-1.0.0.dist-info/entry_points.txt
d3nav-1.0.0.dist-info/top_level.txt
d3nav-1.0.0.dist-info/RECORD
