Metadata-Version: 2.4
Name: d3nav
Version: 1.0.0
Summary: D³Nav: Data-Driven Driving Agents for Autonomous Vehicles in Unstructured Traffic
Home-page: https://github.com/AdityaNG/d3_nav/
Author: AdityaNG
License-File: LICENSE
Requires-Dist: torch
Requires-Dist: torchvision
Requires-Dist: numpy
Requires-Dist: tqdm
Requires-Dist: opencv-python
Requires-Dist: matplotlib
Requires-Dist: timm==0.6.12
Requires-Dist: scipy
Requires-Dist: einops>=0.6.1
Requires-Dist: lpips>=0.1.4
Requires-Dist: scikit-image
Requires-Dist: pyquaternion>=0.9.9
Requires-Dist: transformers>=4.32.1
Requires-Dist: tabulate>=0.9.0
Requires-Dist: scikit-learn
Requires-Dist: lightning
Requires-Dist: gdown
Provides-Extra: test
Requires-Dist: pytest; extra == "test"
Requires-Dist: coverage; extra == "test"
Requires-Dist: flake8; extra == "test"
Requires-Dist: black; extra == "test"
Requires-Dist: isort; extra == "test"
Requires-Dist: pytest-cov; extra == "test"
Requires-Dist: mypy; extra == "test"
Requires-Dist: gitchangelog; extra == "test"
Requires-Dist: mkdocs; extra == "test"
Requires-Dist: lark; extra == "test"
Dynamic: author
Dynamic: description
Dynamic: description-content-type
Dynamic: home-page
Dynamic: license-file
Dynamic: provides-extra
Dynamic: requires-dist
Dynamic: summary
